MANIFEST.in
README.rst
setup.py
django_suit_redactor.egg-info/PKG-INFO
django_suit_redactor.egg-info/SOURCES.txt
django_suit_redactor.egg-info/dependency_links.txt
django_suit_redactor.egg-info/not-zip-safe
django_suit_redactor.egg-info/top_level.txt
suit_redactor/__init__.py
suit_redactor/models.py
suit_redactor/widgets.py
suit_redactor/static/suit-redactor/redactor/ensure.jquery.js
suit_redactor/static/suit-redactor/redactor/redactor.css
suit_redactor/static/suit-redactor/redactor/redactor.js
suit_redactor/static/suit-redactor/redactor/redactor.min.js
suit_redactor/static/suit-redactor/redactor/style.css