Metadata-Version: 1.1
Name: django-suit-redactor
Version: 0.0.3
Summary: Imperavi Redactor (WYSIWYG editor) integration app for Django admin. http://imperavi.com/redactor/
Home-page: https://github.com/darklow/django-suit-redactor
Author: Kaspars Sprogis (darklow)
Author-email: info@djangosuit.com
License: UNKNOWN
Platform: UNKNOWN
Classifier: Development Status :: 5 - Production/Stable
Classifier: Framework :: Django
Classifier: License :: Free for non-commercial use
Classifier: Intended Audience :: Developers
Classifier: Intended Audience :: System Administrators
Classifier: Programming Language :: Python
Classifier: Environment :: Web Environment
Classifier: Topic :: Software Development :: User Interfaces
